nutcli/__init__.py
nutcli/commands.py
nutcli/decorators.py
nutcli/exceptions.py
nutcli/parser.py
nutcli/runner.py
nutcli/shell.py
nutcli/tasks.py
nutcli/utils.py
nutcli-1.2.dist-info/LICENSE
nutcli-1.2.dist-info/METADATA
nutcli-1.2.dist-info/WHEEL
nutcli-1.2.dist-info/top_level.txt
nutcli-1.2.dist-info/RECORD
