Metadata-Version: 2.1
Name: nutcli
Version: 1.2
Summary: Build robust command line interface fast.
Home-page: https://github.com/pbrezina/python-nutcli
Author: Pavel Březina
Author-email: brezinapavel@gmail.com
License: UNKNOWN
Platform: UNKNOWN
Classifier: License :: OSI Approved :: GNU General Public License v3 (GPLv3)
Classifier: Programming Language :: Python :: 3
Classifier: Operating System :: POSIX :: Linux
Requires-Python: >=3.6
License-File: LICENSE
Requires-Dist: colorama
